setup.cfg
setup.py
gtasks/__init__.py
gtasks/credentials.json
gtasks/gtaskobject.py
gtasks/gtasks.py
gtasks/misc.py
gtasks/task.py
gtasks/tasklist.py
gtasks/timeconversion.py
gtasks.egg-info/PKG-INFO
gtasks.egg-info/SOURCES.txt
gtasks.egg-info/dependency_links.txt
gtasks.egg-info/requires.txt
gtasks.egg-info/top_level.txt