Metadata-Version: 1.0
Name: gtasks
Version: 0.1.2
Summary: A better Google Tasks Python module
Home-page: https://github.com/benjaminwhite/Gtasks
Author: Benjamin White
Author-email: ben.white@berkeley.edu
License: MIT
Keywords: google,tasks,task,gtasks,gtask
Platform: UNKNOWN
